LICENSE
MANIFEST.in
README.rst
setup.py
django_ssheepdog.egg-info/PKG-INFO
django_ssheepdog.egg-info/SOURCES.txt
django_ssheepdog.egg-info/dependency_links.txt
django_ssheepdog.egg-info/requires.txt
django_ssheepdog.egg-info/top_level.txt
src/__init__.py
src/manage.py
src/settings-heroku.py
src/settings.py
src/urls.py
ssheepdog/__init__.py
ssheepdog/admin.py
ssheepdog/fields.py
ssheepdog/forms.py
ssheepdog/middleware.py
ssheepdog/models.py
ssheepdog/tasks.py
ssheepdog/tests.py
ssheepdog/urls.py
ssheepdog/utils.py
ssheepdog/views.py
ssheepdog/management/__init__.py
ssheepdog/management/commands/__init__.py
ssheepdog/management/commands/runtask.py
ssheepdog/management/commands/update_ssh.py
ssheepdog/migrations/0001_initial.py
ssheepdog/migrations/0002_auto__add_field_machine_port.py
ssheepdog/migrations/0003_auto__add_field_login_is_dirty.py
ssheepdog/migrations/0004_auto__add_field_machine_is_down.py
ssheepdog/migrations/0005_auto__add_applicationkey__add_field_login_application_key.py
ssheepdog/migrations/0006_auto__del_field_userprofile_is_active.py
ssheepdog/migrations/0007_auto__add_loginlog__chg_field_applicationkey_public_key__chg_field_use.py
ssheepdog/migrations/0008_add_permissions.py
ssheepdog/migrations/0009_auto__add_field_login_additional_public_keys__chg_field_userprofile_ss.py
ssheepdog/migrations/0010_auto__add_field_machine_manual.py
ssheepdog/migrations/__init__.py
ssheepdog/static/css/base.css
ssheepdog/static/css/bootstrap.min.css
ssheepdog/static/css/bootstrap.min.responsive.css
ssheepdog/static/images/cross-gray.png
ssheepdog/static/images/cross.png
ssheepdog/static/images/gray-grad.png
ssheepdog/static/images/tick-gray.png
ssheepdog/static/images/tick.png
ssheepdog/static/img/glyphicons-halflings-white.png
ssheepdog/static/img/glyphicons-halflings.png
ssheepdog/static/js/bootstrap.min.js
ssheepdog/static/js/jquery-1.7.1.js
ssheepdog/static/js/jquery-client.js
ssheepdog/templates/403.html
ssheepdog/templates/404.html
ssheepdog/templates/500.html
ssheepdog/templates/base.html
ssheepdog/templates/confirm_toggle.html
ssheepdog/templates/login_view.html
ssheepdog/templates/user_view.html
ssheepdog/templates/view_grid.html
