Metadata-Version: 1.0
Name: django-ssheepdog
Version: 0.2.0
Summary: django-ssheepdog is a public ssh key management tool for teams of programmers
Home-page: https://github.com/SheepDogInc/django-ssheepdog
Author: SheepDogInc
Author-email: development@sheepdoginc.ca
License: UNKNOWN
Platform: UNKNOWN
Classifier: Framework :: Django
Classifier: Intended Audience :: Developers
Classifier: Intended Audience :: System Administrators
Classifier: Topic :: Software Development
